README
setup.py
pc987_sulib/__init__.py
pc987_sulib/pc987_sulib.py
pc987_sulib.egg-info/PKG-INFO
pc987_sulib.egg-info/SOURCES.txt
pc987_sulib.egg-info/dependency_links.txt
pc987_sulib.egg-info/not-zip-safe
pc987_sulib.egg-info/top_level.txt