Metadata-Version: 1.0
Name: pc987-sulib
Version: 0.221
Summary: The most useful Python module
Home-page: http://github.com/somewher/out/there
Author: Author Name
Author-email: authorname@email.com
License: MIT
Platform: UNKNOWN
